bfk_authsystem/__init__.py
bfk_authsystem/api_client.py
bfk_authsystem/cache.py
bfk_authsystem/circuit_breaker.py
bfk_authsystem/exceptions.py
bfk_authsystem/hardware.py
bfk_authsystem/hardware_validator.py
bfk_authsystem/models.py
bfk_authsystem/retry_handler.py
bfk_authsystem/validator.py
bfk_authsystem/docs/API_INTEGRATION.md
bfk_authsystem/docs/__init__.py
bfk_authsystem/docs/bfk_authsystem_example.py
bfk_authsystem/ui/__init__.py
bfk_authsystem/ui/base_dialog.py
bfk_authsystem/ui/change_password_dialog.py
bfk_authsystem/ui/force_change_password_dialog.py
bfk_authsystem/ui/forgot_password_dialog.py
bfk_authsystem/ui/license_key_dialog.py
bfk_authsystem/ui/login_dialog.py
bfk_authsystem/ui/mfa_dialog.py
bfk_authsystem/ui/recovery_codes_dialog.py
bfk_authsystem/ui/regenerate_codes_dialog.py
bfk_authsystem/ui/session_management_dialog.py
bfk_authsystem/ui/status_dialog.py
bfk_authsystem-1.2.3.dist-info/licenses/LICENSE
tests/__init__.py
tests/conftest.py
tests/test_api_client.py
tests/test_exceptions.py
tests/test_ui_validation.py
tests/test_validator.py
bfk_authsystem-1.2.3.dist-info/METADATA
bfk_authsystem-1.2.3.dist-info/WHEEL
bfk_authsystem-1.2.3.dist-info/top_level.txt
bfk_authsystem-1.2.3.dist-info/RECORD
