Metadata-Version: 2.4
Name: bfk-authsystem
Version: 1.2.3
Summary: Biblioteca cliente para integracao com BFK AuthSystem
Home-page: https://github.com/bfkons/BFK-AuthSystem
Author: BFK Engenharia
Author-email: bruno@bfk.eng.br
Keywords: license,authentication,mfa,security
Classifier: Development Status :: 4 - Beta
Classifier: Intended Audience :: Developers
Classifier: License :: OSI Approved :: MIT License
Classifier: Operating System :: OS Independent
Classifier: Programming Language :: Python :: 3
Classifier: Programming Language :: Python :: 3.8
Classifier: Programming Language :: Python :: 3.9
Classifier: Programming Language :: Python :: 3.10
Classifier: Programming Language :: Python :: 3.11
Classifier: Programming Language :: Python :: 3.12
Classifier: Topic :: Security
Classifier: Topic :: Software Development :: Libraries :: Python Modules
Requires-Python: >=3.8
License-File: LICENSE
Requires-Dist: requests>=2.31.0
Requires-Dist: cryptography>=41.0.0
Provides-Extra: ui
Requires-Dist: PyQt5>=5.15.0; extra == "ui"
Provides-Extra: hardware
Requires-Dist: psutil>=5.9.0; extra == "hardware"
Provides-Extra: full
Requires-Dist: PyQt5>=5.15.0; extra == "full"
Requires-Dist: psutil>=5.9.0; extra == "full"
Dynamic: author
Dynamic: author-email
Dynamic: classifier
Dynamic: description
Dynamic: description-content-type
Dynamic: home-page
Dynamic: keywords
Dynamic: license-file
Dynamic: provides-extra
Dynamic: requires-dist
Dynamic: requires-python
Dynamic: summary
